helloworld.py
helloworld1_avborodin-0.0.1.dist-info/METADATA
helloworld1_avborodin-0.0.1.dist-info/WHEEL
helloworld1_avborodin-0.0.1.dist-info/top_level.txt
helloworld1_avborodin-0.0.1.dist-info/RECORD
