Metadata-Version: 2.1
Name: helloworld1-avborodin
Version: 0.0.1
Summary: Say hello
Home-page: UNKNOWN
Author: Andrey Borodin
Author-email: boroddon@gmail.com
License: UNKNOWN
Platform: UNKNOWN
